[
  {
    "pkg_repo": "Classic", 
    "pkg_full_name": "clex-4.6.6-alt1.x86_64.rpm", 
    "pkg": "clex", 
    "pkg_version": "4.6.6", 
    "os": "linux", 
    "distro": "alt"
  }, 
  {
    "pkg_repo": "Repoforge (RPMforge)", 
    "pkg_full_name": "clex-4.4-1.el6.rf.x86_64.rpm", 
    "pkg": "clex", 
    "pkg_version": "4.4", 
    "release": ">=6", 
    "os": "linux", 
    "distro": "centos"
  }, 
  {
    "pkg_repo": "Repoforge (RPMforge)", 
    "pkg_full_name": "clex-4.2-1.el5.rf.x86_64.rpm", 
    "pkg": "clex", 
    "pkg_version": "4.2", 
    "release": ">=5", 
    "os": "linux", 
    "distro": "centos"
  }, 
  {
    "pkg_repo": "Debian Main", 
    "pkg_full_name": "clex_3.15-1_i386.deb", 
    "pkg": "clex", 
    "pkg_version": "3.1", 
    "release": ">=dev", 
    "os": "linux", 
    "distro": "debian"
  }, 
  {
    "pkg_repo": "Debian Main", 
    "pkg_full_name": "clex_3.15-1_i386.deb", 
    "pkg": "clex", 
    "pkg_version": "3.1", 
    "release": ">=8.0", 
    "os": "linux", 
    "distro": "debian"
  }, 
  {
    "pkg_repo": "Debian Main", 
    "pkg_full_name": "clex_3.15-1_i386.deb", 
    "pkg": "clex", 
    "pkg_version": "3.1", 
    "release": ">=7.0", 
    "os": "linux", 
    "distro": "debian"
  }, 
  {
    "pkg_repo": "RPM Sphere", 
    "pkg_full_name": "clex-4.6.patch6-2.1.x86_64.rpm", 
    "pkg": "clex", 
    "pkg_version": "4.6", 
    "release": ">=21", 
    "os": "linux", 
    "distro": "fedora"
  }, 
  {
    "pkg_repo": "RPM Sphere", 
    "pkg_full_name": "clex-4.6.patch6-2.1.x86_64.rpm", 
    "pkg": "clex", 
    "pkg_version": "4.6", 
    "release": ">=20", 
    "os": "linux", 
    "distro": "fedora"
  }, 
  {
    "pkg_repo": "Salix", 
    "pkg_full_name": "clex-4.6.patch5-x86_64-2fg.txz", 
    "pkg": "clex", 
    "pkg_version": "4.6", 
    "release": ">=14.0", 
    "os": "linux", 
    "distro": "slackware"
  }, 
  {
    "pkg_repo": "Ubuntu Universe", 
    "pkg_full_name": "clex_3.15-1_i386.deb", 
    "pkg": "clex", 
    "pkg_version": "3.1", 
    "release": ">=14.10", 
    "os": "linux", 
    "distro": "ubuntu"
  }, 
  {
    "pkg_repo": "Ubuntu Universe", 
    "pkg_full_name": "clex_3.15-1_i386.deb", 
    "pkg": "clex", 
    "pkg_version": "3.1", 
    "release": ">=14.04", 
    "os": "linux", 
    "distro": "ubuntu"
  }
]