[
  {
    "pkg_repo": "Debian Main", 
    "pkg_full_name": "libbobcat3_3.23.01-1_i386.deb", 
    "pkg": "libbobcat3", 
    "pkg_version": "3.2", 
    "release": ">=dev", 
    "os": "linux", 
    "distro": "debian"
  }, 
  {
    "pkg_repo": "Debian Main", 
    "pkg_full_name": "libbobcat3_3.23.01-1_i386.deb", 
    "pkg": "libbobcat3", 
    "pkg_version": "3.2", 
    "release": ">=8.0", 
    "os": "linux", 
    "distro": "debian"
  }, 
  {
    "pkg_repo": "Debian Main", 
    "pkg_full_name": "libbobcat3_3.01.00-1+b1_i386.deb", 
    "pkg": "libbobcat3", 
    "pkg_version": "3.0", 
    "release": ">=7.0", 
    "os": "linux", 
    "distro": "debian"
  }, 
  {
    "pkg_repo": "Ubuntu Universe", 
    "pkg_full_name": "libbobcat3_3.22.00-1ubuntu1_i386.deb", 
    "pkg": "libbobcat3", 
    "pkg_version": "3.2", 
    "release": ">=14.10", 
    "os": "linux", 
    "distro": "ubuntu"
  }
]