[
  {
    "pkg_repo": "Debian Main", 
    "pkg_full_name": "opendkim-tools_2.9.2-2_i386.deb", 
    "pkg": "opendkim-tools", 
    "pkg_version": "2.9.2", 
    "release": ">=dev", 
    "os": "linux", 
    "distro": "debian"
  }, 
  {
    "pkg_repo": "Debian Main", 
    "pkg_full_name": "opendkim-tools_2.9.2-2_i386.deb", 
    "pkg": "opendkim-tools", 
    "pkg_version": "2.9.2", 
    "release": ">=8.0", 
    "os": "linux", 
    "distro": "debian"
  }, 
  {
    "pkg_repo": "Debian Main", 
    "pkg_full_name": "opendkim-tools_2.6.8-4_i386.deb", 
    "pkg": "opendkim-tools", 
    "pkg_version": "2.6.8", 
    "release": ">=7.0", 
    "os": "linux", 
    "distro": "debian"
  }, 
  {
    "pkg_repo": "Ubuntu Universe", 
    "pkg_full_name": "opendkim-tools_2.9.2-1build1_i386.deb", 
    "pkg": "opendkim-tools", 
    "pkg_version": "2.9.2", 
    "release": ">=14.10", 
    "os": "linux", 
    "distro": "ubuntu"
  }, 
  {
    "pkg_repo": "Ubuntu Universe", 
    "pkg_full_name": "opendkim-tools_2.9.1-1_i386.deb", 
    "pkg": "opendkim-tools", 
    "pkg_version": "2.9.1", 
    "release": ">=14.04", 
    "os": "linux", 
    "distro": "ubuntu"
  }
]