[
  {
    "pkg_repo": "Classic", 
    "pkg_full_name": "xorg-xcbproto-devel-1.11-alt1.noarch.rpm", 
    "pkg": "xorg-xcbproto-devel", 
    "pkg_version": "1.1", 
    "os": "linux", 
    "distro": "alt"
  }, 
  {
    "pkg_repo": "Classic", 
    "pkg_full_name": "xorg-xcbproto-devel-1.11-alt1.noarch.rpm", 
    "pkg": "xorg-xcbproto-devel", 
    "pkg_version": "1.1", 
    "os": "linux", 
    "distro": "arch"
  }, 
  {
    "pkg_repo": "Arch Linux Extra", 
    "pkg_full_name": "xcb-proto-1.11-1-any.pkg.tar.xz", 
    "pkg": "xcb-proto", 
    "pkg_version": "1.1", 
    "os": "linux", 
    "distro": "arch"
  }, 
  {
    "pkg_repo": "Classic", 
    "pkg_full_name": "xorg-xcbproto-devel-1.11-alt1.noarch.rpm", 
    "pkg": "xorg-xcbproto-devel", 
    "pkg_version": "1.1", 
    "release": ">=7", 
    "os": "linux", 
    "distro": "centos"
  }, 
  {
    "pkg_repo": "CentOS", 
    "pkg_full_name": "xcb-proto-1.8-3.el7.noarch.rpm", 
    "pkg": "xcb-proto", 
    "pkg_version": "1.8", 
    "release": ">=7", 
    "os": "linux", 
    "distro": "centos"
  }, 
  {
    "pkg_repo": "Classic", 
    "pkg_full_name": "xorg-xcbproto-devel-1.11-alt1.noarch.rpm", 
    "pkg": "xorg-xcbproto-devel", 
    "pkg_version": "1.1", 
    "release": ">=6", 
    "os": "linux", 
    "distro": "centos"
  }, 
  {
    "pkg_repo": "CentOS", 
    "pkg_full_name": "xcb-proto-1.8-3.el6.noarch.rpm", 
    "pkg": "xcb-proto", 
    "pkg_version": "1.8", 
    "release": ">=6", 
    "os": "linux", 
    "distro": "centos"
  }, 
  {
    "pkg_repo": "Classic", 
    "pkg_full_name": "xorg-xcbproto-devel-1.11-alt1.noarch.rpm", 
    "pkg": "xorg-xcbproto-devel", 
    "pkg_version": "1.1", 
    "release": ">=5", 
    "os": "linux", 
    "distro": "centos"
  }, 
  {
    "pkg_repo": "ATrpms Testing", 
    "pkg_full_name": "xcb-proto-1.1-1.el5.noarch.rpm", 
    "pkg": "xcb-proto", 
    "pkg_version": "1.1", 
    "release": ">=5", 
    "os": "linux", 
    "distro": "centos"
  }, 
  {
    "pkg_repo": "Classic", 
    "pkg_full_name": "xorg-xcbproto-devel-1.11-alt1.noarch.rpm", 
    "pkg": "xorg-xcbproto-devel", 
    "pkg_version": "1.1", 
    "release": ">=dev", 
    "os": "linux", 
    "distro": "debian"
  }, 
  {
    "pkg_repo": "Debian Main", 
    "pkg_full_name": "xcb-proto_1.10-1_all.deb", 
    "pkg": "xcb-proto", 
    "pkg_version": "1.1", 
    "release": ">=dev", 
    "os": "linux", 
    "distro": "debian"
  }, 
  {
    "pkg_repo": "Classic", 
    "pkg_full_name": "xorg-xcbproto-devel-1.11-alt1.noarch.rpm", 
    "pkg": "xorg-xcbproto-devel", 
    "pkg_version": "1.1", 
    "release": ">=8.0", 
    "os": "linux", 
    "distro": "debian"
  }, 
  {
    "pkg_repo": "Debian Main", 
    "pkg_full_name": "xcb-proto_1.10-1_all.deb", 
    "pkg": "xcb-proto", 
    "pkg_version": "1.1", 
    "release": ">=8.0", 
    "os": "linux", 
    "distro": "debian"
  }, 
  {
    "pkg_repo": "Classic", 
    "pkg_full_name": "xorg-xcbproto-devel-1.11-alt1.noarch.rpm", 
    "pkg": "xorg-xcbproto-devel", 
    "pkg_version": "1.1", 
    "release": ">=7.0", 
    "os": "linux", 
    "distro": "debian"
  }, 
  {
    "pkg_repo": "Debian Main", 
    "pkg_full_name": "xcb-proto_1.7.1-1_all.deb", 
    "pkg": "xcb-proto", 
    "pkg_version": "1.7.1", 
    "release": ">=7.0", 
    "os": "linux", 
    "distro": "debian"
  }, 
  {
    "pkg_repo": "Classic", 
    "pkg_full_name": "xorg-xcbproto-devel-1.11-alt1.noarch.rpm", 
    "pkg": "xorg-xcbproto-devel", 
    "pkg_version": "1.1", 
    "release": ">=dev", 
    "os": "linux", 
    "distro": "fedora"
  }, 
  {
    "pkg_repo": "Fedora", 
    "pkg_full_name": "xcb-proto-1.11-1.fc23.noarch.rpm", 
    "pkg": "xcb-proto", 
    "pkg_version": "1.1", 
    "release": ">=dev", 
    "os": "linux", 
    "distro": "fedora"
  }, 
  {
    "pkg_repo": "Classic", 
    "pkg_full_name": "xorg-xcbproto-devel-1.11-alt1.noarch.rpm", 
    "pkg": "xorg-xcbproto-devel", 
    "pkg_version": "1.1", 
    "release": ">=22", 
    "os": "linux", 
    "distro": "fedora"
  }, 
  {
    "pkg_repo": "Fedora", 
    "pkg_full_name": "xcb-proto-1.11-1.fc22.noarch.rpm", 
    "pkg": "xcb-proto", 
    "pkg_version": "1.1", 
    "release": ">=22", 
    "os": "linux", 
    "distro": "fedora"
  }, 
  {
    "pkg_repo": "Classic", 
    "pkg_full_name": "xorg-xcbproto-devel-1.11-alt1.noarch.rpm", 
    "pkg": "xorg-xcbproto-devel", 
    "pkg_version": "1.1", 
    "release": ">=21", 
    "os": "linux", 
    "distro": "fedora"
  }, 
  {
    "pkg_repo": "Fedora", 
    "pkg_full_name": "xcb-proto-1.11-1.fc21.noarch.rpm", 
    "pkg": "xcb-proto", 
    "pkg_version": "1.1", 
    "release": ">=21", 
    "os": "linux", 
    "distro": "fedora"
  }, 
  {
    "pkg_repo": "Classic", 
    "pkg_full_name": "xorg-xcbproto-devel-1.11-alt1.noarch.rpm", 
    "pkg": "xorg-xcbproto-devel", 
    "pkg_version": "1.1", 
    "release": ">=20", 
    "os": "linux", 
    "distro": "fedora"
  }, 
  {
    "pkg_repo": "Fedora", 
    "pkg_full_name": "xcb-proto-1.8-3.fc20.noarch.rpm", 
    "pkg": "xcb-proto", 
    "pkg_version": "1.8", 
    "release": ">=20", 
    "os": "linux", 
    "distro": "fedora"
  }, 
  {
    "pkg_repo": "Classic", 
    "pkg_full_name": "xorg-xcbproto-devel-1.11-alt1.noarch.rpm", 
    "pkg": "xorg-xcbproto-devel", 
    "pkg_version": "1.1", 
    "release": ">=14.1", 
    "os": "linux", 
    "distro": "slackware"
  }, 
  {
    "pkg_repo": "Slackware", 
    "pkg_full_name": "xcb-proto-1.8-x86_64-1.txz", 
    "pkg": "xcb-proto", 
    "pkg_version": "1.8", 
    "release": ">=14.1", 
    "os": "linux", 
    "distro": "slackware"
  }, 
  {
    "pkg_repo": "Classic", 
    "pkg_full_name": "xorg-xcbproto-devel-1.11-alt1.noarch.rpm", 
    "pkg": "xorg-xcbproto-devel", 
    "pkg_version": "1.1", 
    "release": ">=14.0", 
    "os": "linux", 
    "distro": "slackware"
  }, 
  {
    "pkg_repo": "Slackware", 
    "pkg_full_name": "xcb-proto-1.7.1-x86_64-3.txz", 
    "pkg": "xcb-proto", 
    "pkg_version": "1.7.1", 
    "release": ">=14.0", 
    "os": "linux", 
    "distro": "slackware"
  }, 
  {
    "pkg_repo": "Classic", 
    "pkg_full_name": "xorg-xcbproto-devel-1.11-alt1.noarch.rpm", 
    "pkg": "xorg-xcbproto-devel", 
    "pkg_version": "1.1", 
    "release": ">=13.37", 
    "os": "linux", 
    "distro": "slackware"
  }, 
  {
    "pkg_repo": "Slackware", 
    "pkg_full_name": "xcb-proto-1.6-noarch-1.txz", 
    "pkg": "xcb-proto", 
    "pkg_version": "1.6", 
    "release": ">=13.37", 
    "os": "linux", 
    "distro": "slackware"
  }, 
  {
    "pkg_repo": "Classic", 
    "pkg_full_name": "xorg-xcbproto-devel-1.11-alt1.noarch.rpm", 
    "pkg": "xorg-xcbproto-devel", 
    "pkg_version": "1.1", 
    "release": ">=14.10", 
    "os": "linux", 
    "distro": "ubuntu"
  }, 
  {
    "pkg_repo": "Ubuntu Main", 
    "pkg_full_name": "xcb-proto_1.10-1_all.deb", 
    "pkg": "xcb-proto", 
    "pkg_version": "1.1", 
    "release": ">=14.10", 
    "os": "linux", 
    "distro": "ubuntu"
  }, 
  {
    "pkg_repo": "Classic", 
    "pkg_full_name": "xorg-xcbproto-devel-1.11-alt1.noarch.rpm", 
    "pkg": "xorg-xcbproto-devel", 
    "pkg_version": "1.1", 
    "release": ">=14.04", 
    "os": "linux", 
    "distro": "ubuntu"
  }, 
  {
    "pkg_repo": "Ubuntu Main", 
    "pkg_full_name": "xcb-proto_1.10-1_all.deb", 
    "pkg": "xcb-proto", 
    "pkg_version": "1.1", 
    "release": ">=14.04", 
    "os": "linux", 
    "distro": "ubuntu"
  }
]