[
  {
    "pkg_repo": "Classic", 
    "pkg_full_name": "crossfire-1.11.0-alt1.qa6.x86_64.rpm", 
    "pkg": "crossfire", 
    "pkg_version": "1.1", 
    "os": "linux", 
    "distro": "alt"
  }, 
  {
    "pkg_repo": "Debian Main", 
    "pkg_full_name": "crossfire-server_1.71.0+dfsg1-1_i386.deb", 
    "pkg": "crossfire-server", 
    "pkg_version": "1.7", 
    "release": ">=dev", 
    "os": "linux", 
    "distro": "debian"
  }, 
  {
    "pkg_repo": "Classic", 
    "pkg_full_name": "crossfire-1.11.0-alt1.qa6.x86_64.rpm", 
    "pkg": "crossfire", 
    "pkg_version": "1.1", 
    "release": ">=dev", 
    "os": "linux", 
    "distro": "debian"
  }, 
  {
    "pkg_repo": "Debian Main", 
    "pkg_full_name": "crossfire-server_1.71.0+dfsg1-1_i386.deb", 
    "pkg": "crossfire-server", 
    "pkg_version": "1.7", 
    "release": ">=8.0", 
    "os": "linux", 
    "distro": "debian"
  }, 
  {
    "pkg_repo": "Classic", 
    "pkg_full_name": "crossfire-1.11.0-alt1.qa6.x86_64.rpm", 
    "pkg": "crossfire", 
    "pkg_version": "1.1", 
    "release": ">=8.0", 
    "os": "linux", 
    "distro": "debian"
  }, 
  {
    "pkg_repo": "Debian Main", 
    "pkg_full_name": "crossfire-server_1.70.0-1_i386.deb", 
    "pkg": "crossfire-server", 
    "pkg_version": "1.7", 
    "release": ">=7.0", 
    "os": "linux", 
    "distro": "debian"
  }, 
  {
    "pkg_repo": "Classic", 
    "pkg_full_name": "crossfire-1.11.0-alt1.qa6.x86_64.rpm", 
    "pkg": "crossfire", 
    "pkg_version": "1.1", 
    "release": ">=7.0", 
    "os": "linux", 
    "distro": "debian"
  }, 
  {
    "pkg_repo": "OpenMandriva Contrib", 
    "pkg_full_name": "crossfire-server-1.70.0-1-omv2013.0.x86_64.rpm", 
    "pkg": "crossfire-server", 
    "pkg_version": "1.7", 
    "release": ">=dev", 
    "os": "linux", 
    "distro": "mandriva"
  }, 
  {
    "pkg_repo": "Classic", 
    "pkg_full_name": "crossfire-1.11.0-alt1.qa6.x86_64.rpm", 
    "pkg": "crossfire", 
    "pkg_version": "1.1", 
    "release": ">=dev", 
    "os": "linux", 
    "distro": "mandriva"
  }, 
  {
    "pkg_repo": "OpenMandriva Contrib", 
    "pkg_full_name": "crossfire-server-1.70.0-1-omv2013.0.x86_64.rpm", 
    "pkg": "crossfire-server", 
    "pkg_version": "1.7", 
    "release": ">=2014.1", 
    "os": "linux", 
    "distro": "mandriva"
  }, 
  {
    "pkg_repo": "Classic", 
    "pkg_full_name": "crossfire-1.11.0-alt1.qa6.x86_64.rpm", 
    "pkg": "crossfire", 
    "pkg_version": "1.1", 
    "release": ">=2014.1", 
    "os": "linux", 
    "distro": "mandriva"
  }, 
  {
    "pkg_repo": "OpenMandriva Contrib", 
    "pkg_full_name": "crossfire-server-1.70.0-1-omv2013.0.x86_64.rpm", 
    "pkg": "crossfire-server", 
    "pkg_version": "1.7", 
    "release": ">=2013.0", 
    "os": "linux", 
    "distro": "mandriva"
  }, 
  {
    "pkg_repo": "Classic", 
    "pkg_full_name": "crossfire-1.11.0-alt1.qa6.x86_64.rpm", 
    "pkg": "crossfire", 
    "pkg_version": "1.1", 
    "release": ">=2013.0", 
    "os": "linux", 
    "distro": "mandriva"
  }, 
  {
    "pkg_repo": "ROSA Contrib", 
    "pkg_full_name": "crossfire-server-1.70.0-2-rosa2014.1.x86_64.rpm", 
    "pkg": "crossfire-server", 
    "pkg_version": "1.7", 
    "release": ">=2014.1", 
    "os": "linux", 
    "distro": "rosa"
  }, 
  {
    "pkg_repo": "Classic", 
    "pkg_full_name": "crossfire-1.11.0-alt1.qa6.x86_64.rpm", 
    "pkg": "crossfire", 
    "pkg_version": "1.1", 
    "release": ">=2014.1", 
    "os": "linux", 
    "distro": "rosa"
  }, 
  {
    "pkg_repo": "ROSA Contrib", 
    "pkg_full_name": "crossfire-server-1.70.0-1-rosa2012.1.x86_64.rpm", 
    "pkg": "crossfire-server", 
    "pkg_version": "1.7", 
    "release": ">=3", 
    "os": "linux", 
    "distro": "rosa"
  }, 
  {
    "pkg_repo": "Classic", 
    "pkg_full_name": "crossfire-1.11.0-alt1.qa6.x86_64.rpm", 
    "pkg": "crossfire", 
    "pkg_version": "1.1", 
    "release": ">=3", 
    "os": "linux", 
    "distro": "rosa"
  }, 
  {
    "pkg_repo": "Ubuntu Universe", 
    "pkg_full_name": "crossfire-server_1.71.0+dfsg1-1_i386.deb", 
    "pkg": "crossfire-server", 
    "pkg_version": "1.7", 
    "release": ">=14.10", 
    "os": "linux", 
    "distro": "ubuntu"
  }, 
  {
    "pkg_repo": "Classic", 
    "pkg_full_name": "crossfire-1.11.0-alt1.qa6.x86_64.rpm", 
    "pkg": "crossfire", 
    "pkg_version": "1.1", 
    "release": ">=14.10", 
    "os": "linux", 
    "distro": "ubuntu"
  }, 
  {
    "pkg_repo": "Ubuntu Universe", 
    "pkg_full_name": "crossfire-server_1.70.0-1_i386.deb", 
    "pkg": "crossfire-server", 
    "pkg_version": "1.7", 
    "release": ">=14.04", 
    "os": "linux", 
    "distro": "ubuntu"
  }, 
  {
    "pkg_repo": "Classic", 
    "pkg_full_name": "crossfire-1.11.0-alt1.qa6.x86_64.rpm", 
    "pkg": "crossfire", 
    "pkg_version": "1.1", 
    "release": ">=14.04", 
    "os": "linux", 
    "distro": "ubuntu"
  }
]