[
  {
    "pkg_repo": "Debian Main", 
    "pkg_full_name": "python3-sqlalchemy_0.9.8+dfsg-0.1_all.deb", 
    "pkg": "python3-sqlalchemy", 
    "pkg_version": "0.9.8", 
    "release": ">=dev", 
    "os": "linux", 
    "distro": "debian"
  }, 
  {
    "pkg_repo": "Debian Main", 
    "pkg_full_name": "python3-sqlalchemy_0.9.8+dfsg-0.1_all.deb", 
    "pkg": "python3-sqlalchemy", 
    "pkg_version": "0.9.8", 
    "release": ">=8.0", 
    "os": "linux", 
    "distro": "debian"
  }, 
  {
    "pkg_repo": "Debian Main", 
    "pkg_full_name": "python3-sqlalchemy_0.7.8-1_all.deb", 
    "pkg": "python3-sqlalchemy", 
    "pkg_version": "0.7.8", 
    "release": ">=7.0", 
    "os": "linux", 
    "distro": "debian"
  }, 
  {
    "pkg_repo": "Fedora", 
    "pkg_full_name": "python3-sqlalchemy-0.9.8-1.fc22.x86_64.rpm", 
    "pkg": "python3-sqlalchemy", 
    "pkg_version": "0.9.8", 
    "release": ">=dev", 
    "os": "linux", 
    "distro": "fedora"
  }, 
  {
    "pkg_repo": "Fedora", 
    "pkg_full_name": "python3-sqlalchemy-0.9.8-1.fc22.x86_64.rpm", 
    "pkg": "python3-sqlalchemy", 
    "pkg_version": "0.9.8", 
    "release": ">=22", 
    "os": "linux", 
    "distro": "fedora"
  }, 
  {
    "pkg_repo": "Fedora", 
    "pkg_full_name": "python3-sqlalchemy-0.9.8-1.fc21.x86_64.rpm", 
    "pkg": "python3-sqlalchemy", 
    "pkg_version": "0.9.8", 
    "release": ">=21", 
    "os": "linux", 
    "distro": "fedora"
  }, 
  {
    "pkg_repo": "Fedora Updates", 
    "pkg_full_name": "python3-sqlalchemy-0.8.7-1.fc20.x86_64.rpm", 
    "pkg": "python3-sqlalchemy", 
    "pkg_version": "0.8.7", 
    "release": ">=20", 
    "os": "linux", 
    "distro": "fedora"
  }, 
  {
    "pkg_repo": "Ubuntu Main", 
    "pkg_full_name": "python3-sqlalchemy_0.9.7-1_all.deb", 
    "pkg": "python3-sqlalchemy", 
    "pkg_version": "0.9.7", 
    "release": ">=14.10", 
    "os": "linux", 
    "distro": "ubuntu"
  }, 
  {
    "pkg_repo": "Ubuntu Main", 
    "pkg_full_name": "python3-sqlalchemy_0.8.4-1build1_all.deb", 
    "pkg": "python3-sqlalchemy", 
    "pkg_version": "0.8.4", 
    "release": ">=14.04", 
    "os": "linux", 
    "distro": "ubuntu"
  }
]