[
  {
    "pkg_repo": "Debian Main", 
    "pkg_full_name": "maint-guide-ru_1.2.35_all.deb", 
    "pkg": "maint-guide-ru", 
    "pkg_version": "1.2.3", 
    "release": ">=dev", 
    "os": "linux", 
    "distro": "debian"
  }, 
  {
    "pkg_repo": "Debian Main", 
    "pkg_full_name": "maint-guide-ru_1.2.35_all.deb", 
    "pkg": "maint-guide-ru", 
    "pkg_version": "1.2.3", 
    "release": ">=8.0", 
    "os": "linux", 
    "distro": "debian"
  }, 
  {
    "pkg_repo": "Debian Main", 
    "pkg_full_name": "maint-guide-ru_1.2.31_all.deb", 
    "pkg": "maint-guide-ru", 
    "pkg_version": "1.2.3", 
    "release": ">=7.0", 
    "os": "linux", 
    "distro": "debian"
  }, 
  {
    "pkg_repo": "Ubuntu Universe", 
    "pkg_full_name": "maint-guide-ru_1.2.33_all.deb", 
    "pkg": "maint-guide-ru", 
    "pkg_version": "1.2.3", 
    "release": ">=14.10", 
    "os": "linux", 
    "distro": "ubuntu"
  }
]