[
  {
    "pkg_repo": "Debian Main", 
    "pkg_full_name": "python-unshare_0.1-2_i386.deb", 
    "pkg": "python-unshare", 
    "pkg_version": "0.1", 
    "release": ">=dev", 
    "os": "linux", 
    "distro": "debian"
  }, 
  {
    "pkg_repo": "Debian Main", 
    "pkg_full_name": "python-unshare_0.1-2_i386.deb", 
    "pkg": "python-unshare", 
    "pkg_version": "0.1", 
    "release": ">=8.0", 
    "os": "linux", 
    "distro": "debian"
  }, 
  {
    "pkg_repo": "Debian Main", 
    "pkg_full_name": "python-unshare_0.1-2_i386.deb", 
    "pkg": "python-unshare", 
    "pkg_version": "0.1", 
    "release": ">=7.0", 
    "os": "linux", 
    "distro": "debian"
  }, 
  {
    "pkg_repo": "Ubuntu Universe", 
    "pkg_full_name": "python-unshare_0.1-2_i386.deb", 
    "pkg": "python-unshare", 
    "pkg_version": "0.1", 
    "release": ">=14.10", 
    "os": "linux", 
    "distro": "ubuntu"
  }
]