[
  {
    "pkg_repo": "Debian Main", 
    "pkg_full_name": "python-hamcrest_1.8.0-1_all.deb", 
    "pkg": "python-hamcrest", 
    "pkg_version": "1.8.0", 
    "release": ">=dev", 
    "os": "linux", 
    "distro": "debian"
  }, 
  {
    "pkg_repo": "Debian Main", 
    "pkg_full_name": "python-hamcrest_1.8.0-1_all.deb", 
    "pkg": "python-hamcrest", 
    "pkg_version": "1.8.0", 
    "release": ">=8.0", 
    "os": "linux", 
    "distro": "debian"
  }, 
  {
    "pkg_repo": "Debian Main", 
    "pkg_full_name": "python-hamcrest_1.6-1_all.deb", 
    "pkg": "python-hamcrest", 
    "pkg_version": "1.6", 
    "release": ">=7.0", 
    "os": "linux", 
    "distro": "debian"
  }, 
  {
    "pkg_repo": "Ubuntu Universe", 
    "pkg_full_name": "python-hamcrest_1.8.0-1_all.deb", 
    "pkg": "python-hamcrest", 
    "pkg_version": "1.8.0", 
    "release": ">=14.10", 
    "os": "linux", 
    "distro": "ubuntu"
  }
]