[
  {
    "pkg_repo": "Debian Main", 
    "pkg_full_name": "gstreamer1.0-plugins-good-doc_1.4.4-2_all.deb", 
    "pkg": "gstreamer", 
    "pkg_version": "1.0", 
    "release": ">=dev", 
    "os": "linux", 
    "distro": "debian"
  }, 
  {
    "pkg_repo": "Debian Main", 
    "pkg_full_name": "gstreamer1.0-plugins-good-doc_1.4.4-2_all.deb", 
    "pkg": "gstreamer", 
    "pkg_version": "1.0", 
    "release": ">=8.0", 
    "os": "linux", 
    "distro": "debian"
  }, 
  {
    "pkg_repo": "Debian Backports Main", 
    "pkg_full_name": "gstreamer1.0-plugins-good-doc_1.2.4-1~bpo70+1_all.deb", 
    "pkg": "gstreamer", 
    "pkg_version": "1.0", 
    "release": ">=7.0", 
    "os": "linux", 
    "distro": "debian"
  }, 
  {
    "pkg_repo": "Ubuntu Main", 
    "pkg_full_name": "gstreamer1.0-plugins-good-doc_1.4.3-1ubuntu1_all.deb", 
    "pkg": "gstreamer", 
    "pkg_version": "1.0", 
    "release": ">=14.10", 
    "os": "linux", 
    "distro": "ubuntu"
  }
]