[
  {
    "pkg_repo": "Debian Main", 
    "pkg_full_name": "openssh-sftp-server_6.7p1-5_i386.deb", 
    "pkg": "openssh-sftp-server", 
    "pkg_version": "6.7", 
    "release": ">=dev", 
    "os": "linux", 
    "distro": "debian"
  }, 
  {
    "pkg_repo": "Debian Main", 
    "pkg_full_name": "openssh-sftp-server_6.7p1-3_i386.deb", 
    "pkg": "openssh-sftp-server", 
    "pkg_version": "6.7", 
    "release": ">=8.0", 
    "os": "linux", 
    "distro": "debian"
  }, 
  {
    "pkg_repo": "Debian Backports Main", 
    "pkg_full_name": "openssh-sftp-server_6.6p1-4~bpo70+1_i386.deb", 
    "pkg": "openssh-sftp-server", 
    "pkg_version": "6.6", 
    "release": ">=7.0", 
    "os": "linux", 
    "distro": "debian"
  }, 
  {
    "pkg_repo": "Ubuntu Main", 
    "pkg_full_name": "openssh-sftp-server_6.6p1-8_i386.deb", 
    "pkg": "openssh-sftp-server", 
    "pkg_version": "6.6", 
    "release": ">=14.10", 
    "os": "linux", 
    "distro": "ubuntu"
  }
]